VERILOG/VERILOG Files/circuit.v
module D_flip_flop (
    input D, 
    input clk,  
    input rst,   
    output reg Q 
);

    always @(posedge clk or posedge rst) begin
        if (rst) begin
            Q <= 1'b0; 
        end else begin
            Q <= D;    
        end
    end

endmodule

module cla_4bit (
    input a0, a1, a2, a3, 
    input b0, b1, b2, b3, 
    input cin,         
    output s0, s1, s2, s3, 
    output cout           
);
    wire [3:0] A, B;       
    wire [3:0] P, G;    
    wire [3:0] C;         

    assign A = {a3, a2, a1, a0};
    assign B = {b3, b2, b1, b0};

    // propagate and generate
    assign P = A ^ B;
    assign G = A & B;

    // carry 
    assign C[0] = cin;
    assign C[1] = G[0] | (P[0] & cin);
    assign C[2] = G[1] | (P[1] & C[1]);
    assign C[3] = G[2] | (P[2] & C[2]);
    assign cout = G[3] | (P[3] & C[3]);

    // sum
    assign {s3, s2, s1, s0} = P ^ C;

endmodule


module circuit (
    input [3:0] A, B,    
    input Cin, clk, rst,
    output [3:0] S,      
    output Cout         
);
    wire [3:0] DFF_A, DFF_B; 
    wire DFF_Cin;           
    wire [3:0] DFF_S;        
    wire DFF_Cout;          

    D_flip_flop dff_A0 (.D(A[0]), .clk(clk), .rst(rst), .Q(DFF_A[0]));
    D_flip_flop dff_A1 (.D(A[1]), .clk(clk), .rst(rst), .Q(DFF_A[1]));
    D_flip_flop dff_A2 (.D(A[2]), .clk(clk), .rst(rst), .Q(DFF_A[2]));
    D_flip_flop dff_A3 (.D(A[3]), .clk(clk), .rst(rst), .Q(DFF_A[3]));
    
    D_flip_flop dff_B0 (.D(B[0]), .clk(clk), .rst(rst), .Q(DFF_B[0]));
    D_flip_flop dff_B1 (.D(B[1]), .clk(clk), .rst(rst), .Q(DFF_B[1]));
    D_flip_flop dff_B2 (.D(B[2]), .clk(clk), .rst(rst), .Q(DFF_B[2]));
    D_flip_flop dff_B3 (.D(B[3]), .clk(clk), .rst(rst), .Q(DFF_B[3]));
    
    D_flip_flop dff_Cin (.D(Cin), .clk(clk), .rst(rst), .Q(DFF_Cin));

    cla_4bit cla (
        .a0(DFF_A[0]), .a1(DFF_A[1]), .a2(DFF_A[2]), .a3(DFF_A[3]),
        .b0(DFF_B[0]), .b1(DFF_B[1]), .b2(DFF_B[2]), .b3(DFF_B[3]),
        .cin(DFF_Cin),
        .s0(DFF_S[0]), .s1(DFF_S[1]), .s2(DFF_S[2]), .s3(DFF_S[3]),
        .cout(DFF_Cout)
    );

    D_flip_flop dff_S0 (.D(DFF_S[0]), .clk(clk), .rst(rst), .Q(S[0]));
    D_flip_flop dff_S1 (.D(DFF_S[1]), .clk(clk), .rst(rst), .Q(S[1]));
    D_flip_flop dff_S2 (.D(DFF_S[2]), .clk(clk), .rst(rst), .Q(S[2]));
    D_flip_flop dff_S3 (.D(DFF_S[3]), .clk(clk), .rst(rst), .Q(S[3]));

    D_flip_flop dff_Cout (.D(DFF_Cout), .clk(clk), .rst(rst), .Q(Cout));

endmodule

VERILOG/VERILOG Files/circuit_tb.v
module circuit_testbench;
    reg [3:0] A, B;    
    reg Cin, clk, rst;  
    wire [3:0] S;      
    wire Cout;          

    wire [3:0] DFF_A, DFF_B; 
    wire DFF_Cin;           
    wire [3:0] DFF_S;        
    wire DFF_Cout;          

    circuit uut (
        .A(A),
        .B(B),
        .Cin(Cin),
        .clk(clk),
        .rst(rst),
        .S(S),
        .Cout(Cout)
    );

    assign DFF_A = uut.DFF_A;
    assign DFF_B = uut.DFF_B;
    assign DFF_Cin = uut.DFF_Cin;
    assign DFF_S = uut.DFF_S;
    assign DFF_Cout = uut.DFF_Cout;

    always #5 clk = ~clk;

    initial begin
        $dumpfile("circuit.vcd");  
        $dumpvars(0, circuit_testbench);  

        clk = 0; rst = 1;         
        #10 rst = 0;                

        // Test cases
        A = 4'b1010; B = 4'b0101; Cin = 0; #10;
        A = 4'b1100; B = 4'b0011; Cin = 0; #10;
        A = 4'b0001; B = 4'b0010; Cin = 0; #10;
        A = 4'b1111; B = 4'b1111; Cin = 0; #10;
        A = 4'b0000; B = 4'b0000; Cin = 0; #10;

        #50 $finish;                
    end

    initial begin
        $monitor("time=%t\t rst=%b\t clk=%b\t A=%b\t B=%b\t Cin=%b\t S=%b\t Cout=%b\t DFF_A=%b\t DFF_B=%b\t DFF_S=%b\t DFF_Cin=%b\t DFF_Cout=%b", 
                 $time, rst, clk, A, B, Cin, S, Cout, DFF_A, DFF_B, DFF_S, DFF_Cin, DFF_Cout);
    end
endmodule

VERILOG/VERILOG Files/circuit.vcd
$date
	Wed Nov 20 16:02:17 2024
$end
$version
	Icarus Verilog
$end
$timescale
	1s
$end
$scope module circuit_testbench $end
$var wire 4 ! DFF_A [3:0] $end
$var wire 4 " DFF_B [3:0] $end
$var wire 1 # DFF_Cin $end
$var wire 1 $ DFF_Cout $end
$var wire 4 % DFF_S [3:0] $end
$var wire 4 & S [3:0] $end
$var wire 1 ' Cout $end
$var reg 4 ( A [3:0] $end
$var reg 4 ) B [3:0] $end
$var reg 1 * Cin $end
$var reg 1 + clk $end
$var reg 1 , rst $end
$scope module uut $end
$var wire 4 - A [3:0] $end
$var wire 4 . B [3:0] $end
$var wire 1 * Cin $end
$var wire 1 + clk $end
$var wire 1 , rst $end
$var wire 4 / S [3:0] $end
$var wire 4 0 DFF_S [3:0] $end
$var wire 1 1 DFF_Cout $end
$var wire 1 2 DFF_Cin $end
$var wire 4 3 DFF_B [3:0] $end
$var wire 4 4 DFF_A [3:0] $end
$var wire 1 ' Cout $end
$scope module cla $end
$var wire 4 5 G [3:0] $end
$var wire 4 6 P [3:0] $end
$var wire 1 7 a0 $end
$var wire 1 8 a1 $end
$var wire 1 9 a2 $end
$var wire 1 : a3 $end
$var wire 1 ; b0 $end
$var wire 1 < b1 $end
$var wire 1 = b2 $end
$var wire 1 > b3 $end
$var wire 1 1 cout $end
$var wire 1 ? s3 $end
$var wire 1 @ s2 $end
$var wire 1 A s1 $end
$var wire 1 B s0 $end
$var wire 1 2 cin $end
$var wire 4 C C [3:0] $end
$var wire 4 D B [3:0] $end
$var wire 4 E A [3:0] $end
$upscope $end
$scope module dff_A0 $end
$var wire 1 F D $end
$var wire 1 + clk $end
$var wire 1 , rst $end
$var reg 1 G Q $end
$upscope $end
$scope module dff_A1 $end
$var wire 1 H D $end
$var wire 1 + clk $end
$var wire 1 , rst $end
$var reg 1 I Q $end
$upscope $end
$scope module dff_A2 $end
$var wire 1 J D $end
$var wire 1 + clk $end
$var wire 1 , rst $end
$var reg 1 K Q $end
$upscope $end
$scope module dff_A3 $end
$var wire 1 L D $end
$var wire 1 + clk $end
$var wire 1 , rst $end
$var reg 1 M Q $end
$upscope $end
$scope module dff_B0 $end
$var wire 1 N D $end
$var wire 1 + clk $end
$var wire 1 , rst $end
$var reg 1 O Q $end
$upscope $end
$scope module dff_B1 $end
$var wire 1 P D $end
$var wire 1 + clk $end
$var wire 1 , rst $end
$var reg 1 Q Q $end
$upscope $end
$scope module dff_B2 $end
$var wire 1 R D $end
$var wire 1 + clk $end
$var wire 1 , rst $end
$var reg 1 S Q $end
$upscope $end
$scope module dff_B3 $end
$var wire 1 T D $end
$var wire 1 + clk $end
$var wire 1 , rst $end
$var reg 1 U Q $end
$upscope $end
$scope module dff_Cin $end
$var wire 1 * D $end
$var wire 1 + clk $end
$var wire 1 , rst $end
$var reg 1 2 Q $end
$upscope $end
$scope module dff_Cout $end
$var wire 1 1 D $end
$var wire 1 + clk $end
$var wire 1 , rst $end
$var reg 1 ' Q $end
$upscope $end
$scope module dff_S0 $end
$var wire 1 V D $end
$var wire 1 + clk $end
$var wire 1 , rst $end
$var reg 1 W Q $end
$upscope $end
$scope module dff_S1 $end
$var wire 1 X D $end
$var wire 1 + clk $end
$var wire 1 , rst $end
$var reg 1 Y Q $end
$upscope $end
$scope module dff_S2 $end
$var wire 1 Z D $end
$var wire 1 + clk $end
$var wire 1 , rst $end
$var reg 1 [ Q $end
$upscope $end
$scope module dff_S3 $end
$var wire 1 \ D $end
$var wire 1 + clk $end
$var wire 1 , rst $end
$var reg 1 ] Q $end
$upscope $end
$upscope $end
$upscope $end
$enddefinitions $end
#0
$dumpvars
0]
0\
0[
0Z
0Y
0X
0W
0V
0U
xT
0S
xR
0Q
xP
0O
xN
0M
xL
0K
xJ
0I
xH
0G
xF
b0 E
b0 D
b0 C
0B
0A
0@
0?
0>
0=
0<
0;
0:
09
08
07
b0 6
b0 5
b0 4
b0 3
02
01
b0 0
b0 /
bx .
bx -
1,
0+
x*
bx )
bx (
0'
b0 &
b0 %
0$
0#
b0 "
b0 !
$end
#5
1+
#10
1N
0P
1R
0T
0F
1H
0J
1L
0+
0*
b101 )
b101 .
b1010 (
b1010 -
0,
#15
1\
1Z
1X
1V
1?
1@
1A
b1111 %
b1111 0
1B
b1111 6
18
b1010 E
1:
1;
b101 D
1=
1I
b1010 !
b1010 4
1M
1O
b101 "
b101 3
1S
1+
#20
1P
0R
0H
1J
0+
b11 )
b11 .
b1100 (
b1100 -
#25
0=
b11 D
1<
19
b1100 E
08
1]
1[
1Y
b1111 &
b1111 /
1W
0S
b11 "
b11 3
1Q
1K
b1100 !
b1100 4
0I
1+
#30
0N
1F
0J
0L
0+
b10 )
b10 .
b1 (
b1 -
#35
0\
0Z
0?
b11 %
b11 0
0@
b11 6
17
09
b1 E
0:
b10 D
0;
1G
0K
b1 !
b1 4
0M
b10 "
b10 3
0O
1+
#40
1N
1R
1T
1H
1J
1L
0+
b1111 )
b1111 .
b1111 (
b1111 -
#45
1\
1Z
1?
1@
1X
0V
b1110 C
1$
11
1A
b1110 %
b1110 0
0B
b1111 5
b0 6
1>
1=
b1111 D
1;
1:
19
b1111 E
18
0]
b11 &
b11 /
0[
1U
1S
b1111 "
b1111 3
1O
1M
1K
b1111 !
b1111 4
1I
1+
#50
0N
0P
0R
0T
0F
0H
0J
0L
0+
b0 )
b0 .
b0 (
b0 -
#55
0\
0Z
0X
0?
0@
b0 %
b0 0
0A
b0 C
0$
01
b0 5
07
08
09
b0 E
0:
0;
0<
0=
b0 D
0>
0G
0I
0K
b0 !
b0 4
0M
0O
0Q
0S
b0 "
b0 3
0U
0W
1[
b1110 &
b1110 /
1]
1'
1+
#60
0+
#65
0'
0]
0[
b0 &
b0 /
0Y
1+
