VERILOG/VERILOG Files/circuit.v
module D_flip_flop (
    input D, 
    input clk,  
    input rst,   
    output reg Q 
);

    always @(posedge clk or posedge rst) begin
        if (rst) begin
            Q <= 1'b0; 
        end else begin
            Q <= D;    
        end
    end

endmodule

module cla_4bit (
    input a0, a1, a2, a3, 
    input b0, b1, b2, b3, 
    input cin,         
    output s0, s1, s2, s3, 
    output cout           
);
    wire [3:0] A, B;       
    wire [3:0] P, G;    
    wire [3:0] C;         

    assign A = {a3, a2, a1, a0};
    assign B = {b3, b2, b1, b0};

    // propagate and generate
    assign P = A ^ B;
    assign G = A & B;

    // carry 
    assign C[0] = cin;
    assign C[1] = G[0] | (P[0] & cin);
    assign C[2] = G[1] | (P[1] & C[1]);
    assign C[3] = G[2] | (P[2] & C[2]);
    assign cout = G[3] | (P[3] & C[3]);

    // sum
    assign {s3, s2, s1, s0} = P ^ C;

endmodule


module circuit (
    input [3:0] A, B,    
    input Cin, clk, rst,
    output [3:0] S,      
    output Cout         
);
    wire [3:0] DFF_A, DFF_B; 
    wire DFF_Cin;           
    wire [3:0] DFF_S;        
    wire DFF_Cout;          

    D_flip_flop dff_A0 (.D(A[0]), .clk(clk), .rst(rst), .Q(DFF_A[0]));
    D_flip_flop dff_A1 (.D(A[1]), .clk(clk), .rst(rst), .Q(DFF_A[1]));
    D_flip_flop dff_A2 (.D(A[2]), .clk(clk), .rst(rst), .Q(DFF_A[2]));
    D_flip_flop dff_A3 (.D(A[3]), .clk(clk), .rst(rst), .Q(DFF_A[3]));
    
    D_flip_flop dff_B0 (.D(B[0]), .clk(clk), .rst(rst), .Q(DFF_B[0]));
    D_flip_flop dff_B1 (.D(B[1]), .clk(clk), .rst(rst), .Q(DFF_B[1]));
    D_flip_flop dff_B2 (.D(B[2]), .clk(clk), .rst(rst), .Q(DFF_B[2]));
    D_flip_flop dff_B3 (.D(B[3]), .clk(clk), .rst(rst), .Q(DFF_B[3]));
    
    D_flip_flop dff_Cin (.D(Cin), .clk(clk), .rst(rst), .Q(DFF_Cin));

    cla_4bit cla (
        .a0(DFF_A[0]), .a1(DFF_A[1]), .a2(DFF_A[2]), .a3(DFF_A[3]),
        .b0(DFF_B[0]), .b1(DFF_B[1]), .b2(DFF_B[2]), .b3(DFF_B[3]),
        .cin(DFF_Cin),
        .s0(DFF_S[0]), .s1(DFF_S[1]), .s2(DFF_S[2]), .s3(DFF_S[3]),
        .cout(DFF_Cout)
    );

    D_flip_flop dff_S0 (.D(DFF_S[0]), .clk(clk), .rst(rst), .Q(S[0]));
    D_flip_flop dff_S1 (.D(DFF_S[1]), .clk(clk), .rst(rst), .Q(S[1]));
    D_flip_flop dff_S2 (.D(DFF_S[2]), .clk(clk), .rst(rst), .Q(S[2]));
    D_flip_flop dff_S3 (.D(DFF_S[3]), .clk(clk), .rst(rst), .Q(S[3]));

    D_flip_flop dff_Cout (.D(DFF_Cout), .clk(clk), .rst(rst), .Q(Cout));

endmodule

VERILOG/VERILOG Files/cla_tb.v
module cla_tb;
    reg a0, a1, a2, a3;   
    reg b0, b1, b2, b3;   
    reg cin, clk, rst;    
    wire s0, s1, s2, s3;  
    wire cout;           

    cla_4bit uut (
        .a0(a0), .a1(a1), .a2(a2), .a3(a3),
        .b0(b0), .b1(b1), .b2(b2), .b3(b3),
        .cin(cin),
        .s0(s0), .s1(s1), .s2(s2), .s3(s3),
        .cout(cout)
    );

    always #2.5 clk = ~clk;

    initial begin
        $dumpfile("cla.vcd");   
        $dumpvars(0, cla_tb);      

        clk = 0; rst = 1;               
        #5 rst = 0;                   

        repeat (30) begin
            {a3, a2, a1, a0} = $random % 16;  
            {b3, b2, b1, b0} = $random % 16;    
            cin = 0;        //assume cin=0 was given in project          
            #5;
        end
        
        #100 $finish;                  
    end

    initial begin
        $monitor("time=%t\t rst=%b\t clk=%b\t a0=%b a1=%b a2=%b a3=%b\t b0=%b b1=%b b2=%b b3=%b\t cin=%b\t s0=%b s1=%b s2=%b s3=%b\t cout=%b", 
                 $time, rst, clk, a0, a1, a2, a3, b0, b1, b2, b3, cin, s0, s1, s2, s3, cout);
    end
endmodule

VERILOG/VERILOG Files/cla.vcd
$date
	Wed Nov 20 16:00:37 2024
$end
$version
	Icarus Verilog
$end
$timescale
	1s
$end
$scope module cla_tb $end
$var wire 1 ! s3 $end
$var wire 1 " s2 $end
$var wire 1 # s1 $end
$var wire 1 $ s0 $end
$var wire 1 % cout $end
$var reg 1 & a0 $end
$var reg 1 ' a1 $end
$var reg 1 ( a2 $end
$var reg 1 ) a3 $end
$var reg 1 * b0 $end
$var reg 1 + b1 $end
$var reg 1 , b2 $end
$var reg 1 - b3 $end
$var reg 1 . cin $end
$var reg 1 / clk $end
$var reg 1 0 rst $end
$scope module uut $end
$var wire 4 1 G [3:0] $end
$var wire 4 2 P [3:0] $end
$var wire 1 & a0 $end
$var wire 1 ' a1 $end
$var wire 1 ( a2 $end
$var wire 1 ) a3 $end
$var wire 1 * b0 $end
$var wire 1 + b1 $end
$var wire 1 , b2 $end
$var wire 1 - b3 $end
$var wire 1 . cin $end
$var wire 1 % cout $end
$var wire 1 ! s3 $end
$var wire 1 " s2 $end
$var wire 1 # s1 $end
$var wire 1 $ s0 $end
$var wire 4 3 C [3:0] $end
$var wire 4 4 B [3:0] $end
$var wire 4 5 A [3:0] $end
$upscope $end
$upscope $end
$enddefinitions $end
#0
$dumpvars
bx 5
bx 4
bx 3
bx 2
bx 1
10
0/
x.
x-
x,
x+
x*
x)
x(
x'
x&
x%
x$
x#
x"
x!
$end
#3
1/
#5
0!
1"
0#
0%
1$
b0 1
b101 2
b0 3
0.
0-
0,
0+
b1 4
1*
0)
1(
0'
b100 5
0&
00
#6
0/
#9
1/
#10
b110 3
1!
1"
0#
0$
b1 1
b1010 2
b11 4
1+
1)
0(
b1001 5
1&
#12
0/
#15
0"
b1010 3
1%
1!
1#
b1101 1
b0 2
1/
1-
1,
b1101 4
0+
b1101 5
1(
#18
0/
#20
0!
b0 3
0%
1"
1#
1$
b0 1
b111 2
0-
0,
1+
b10 4
0*
b101 5
0)
#21
1/
#24
0/
#25
b10 3
1!
1#
0$
b1 1
b1100 2
1-
1,
0+
b1101 4
1*
b1 5
0(
#27
1/
#30
1%
0!
b1000 3
0"
1#
1$
b100 1
b1011 2
0/
1(
1'
b110 5
0&
#33
1/
#35
1!
0#
b1100 1
b1 2
b1100 4
0*
1)
0'
b1101 5
1&
#36
0/
#39
1/
#40
0%
b0 3
1!
1"
1#
b0 1
b1111 2
0-
b110 4
1+
b1001 5
0(
#42
0/
#45
1/
1-
b1010 4
0,
0)
b101 5
1(
#48
0/
#50
0#
b1110 3
1!
1"
0$
b101 1
b10 2
0-
1,
b111 4
1*
#51
1/
#54
0/
#55
1%
b1100 3
0!
0"
0#
1$
b10 1
b1101 2
b1111 4
1-
0(
1'
b10 5
0&
#57
1/
#60
0$
b1100 2
0/
b1110 4
0*
#63
1/
#65
0%
1!
1"
b0 3
1$
b0 1
b1101 2
0-
0+
b101 4
1*
1)
b1000 5
0'
#66
0/
#69
1/
#70
b1000 3
1%
1!
0"
b1100 1
b1 2
b1101 4
1-
b1100 5
1(
#72
0/
#75
1#
b1010 3
0!
0$
b101 1
b1000 2
1/
b101 4
0-
b1101 5
1&
#78
0/
#80
0%
1!
1"
0#
b100 3
1$
b10 1
b1001 2
1-
0,
1+
b1010 4
0*
0)
0(
b11 5
1'
#81
1/
#84
0/
#85
0"
b0 3
0!
0$
b0 1
b0 2
0-
b0 4
0+
0'
b0 5
0&
#87
1/
#90
1%
1"
1#
1$
b1000 1
b111 2
0/
1-
1,
b1101 4
1*
1)
b1010 5
1'
#93
1/
#95
1!
0"
b1100 3
0%
0#
b10 1
b101 2
0-
0,
b11 4
1+
0)
b110 5
1(
#96
0/
#99
1/
#100
0"
1%
b1110 3
0!
0#
0$
b1 1
b1110 2
1)
0'
b1101 5
1&
#102
0/
#105
1/
1,
b101 4
0+
0(
b1011 5
1'
#108
0/
#110
b1100 3
0#
b10 1
b1100 2
1-
1+
b1110 4
0*
0)
b10 5
0&
#111
1/
#114
0/
#115
b1110 3
1!
1"
0#
b1101 1
b10 2
b1111 4
1*
1)
1(
0'
b1101 5
1&
#117
1/
#120
0%
b100 3
1!
0#
1$
b10 1
b1001 2
0/
0,
b1010 4
0*
0)
0(
b11 5
1'
#123
1/
#125
b0 3
1%
0!
1"
1#
0$
b1000 1
b110 2
1,
b1100 4
0+
1)
b1010 5
0&
#126
0/
#129
1/
#130
b100 3
0%
1!
1"
0#
b10 1
b1000 2
0,
b1010 4
1+
b10 5
0)
#132
0/
#135
0"
b0 3
1$
b0 1
b1001 2
1/
b1000 4
0+
0'
b1 5
1&
#138
0/
#140
1%
0!
b1000 1
b1 2
b1001 4
1*
1)
b1000 5
0&
#141
1/
#144
0/
#145
b1100 3
1%
0!
0"
b10 1
b1101 2
0-
1,
1+
b110 4
0*
1'
b1011 5
1&
#147
1/
#150
1"
0$
b110 1
b1000 2
0/
b1110 4
1-
0)
1(
b110 5
0&
